alpha_vantage/__init__.py
alpha_vantage/alphavantage.py
alpha_vantage/cryptocurrencies.py
alpha_vantage/foreignexchange.py
alpha_vantage/fundamentaldata.py
alpha_vantage/sectorperformance.py
alpha_vantage/techindicators.py
alpha_vantage/timeseries.py
alpha_vantage/async_support/__init__.py
alpha_vantage/async_support/alphavantage.py
alpha_vantage/async_support/cryptocurrencies.py
alpha_vantage/async_support/foreignexchange.py
alpha_vantage/async_support/sectorperformance.py
alpha_vantage/async_support/techindicators.py
alpha_vantage/async_support/timeseries.py
alpha_vantage-2.3.0.dist-info/LICENSE.txt
alpha_vantage-2.3.0.dist-info/METADATA
alpha_vantage-2.3.0.dist-info/WHEEL
alpha_vantage-2.3.0.dist-info/top_level.txt
alpha_vantage-2.3.0.dist-info/RECORD
